CHANGELOG
LICENSE
MANIFEST.in
README.rst
setup.cfg
setup.py
MezzanineFor1.7.egg-info/PKG-INFO
MezzanineFor1.7.egg-info/SOURCES.txt
MezzanineFor1.7.egg-info/dependency_links.txt
MezzanineFor1.7.egg-info/entry_points.txt
MezzanineFor1.7.egg-info/not-zip-safe
MezzanineFor1.7.egg-info/requires.txt
MezzanineFor1.7.egg-info/top_level.txt
docs/admin-customization.rst
docs/blog-importing.rst
docs/caching-strategy.rst
docs/colophon.rst
docs/conf.py
docs/configuration.rst
docs/content-architecture.rst
docs/deployment.rst
docs/device-handling.rst
docs/fabfile.rst
docs/frequently-asked-questions.rst
docs/index.rst
docs/inline-editing.rst
docs/model-customization.rst
docs/model-graph.rst
docs/multi-tenancy.rst
docs/overview.rst
docs/packages.rst
docs/search-engine.rst
docs/settings.rst
docs/twitter-integration.rst
docs/user-accounts.rst
docs/utilities.rst
docs/img/dashboard.png
docs/img/graph-small.png
docs/img/graph.png
docs/locale/.placeholder
docs/mezzanine_theme/layout.html
docs/mezzanine_theme/theme.conf
docs/mezzanine_theme/static/mezzanine.css
mezzanine/__init__.py
mezzanine/__init__.pyc
mezzanine/urls.py
mezzanine/accounts/__init__.py
mezzanine/accounts/admin.py
mezzanine/accounts/defaults.py
mezzanine/accounts/forms.py
mezzanine/accounts/models.py
mezzanine/accounts/tests.py
mezzanine/accounts/urls.py
mezzanine/accounts/views.py
mezzanine/accounts/locale/ar/LC_MESSAGES/django.mo
mezzanine/accounts/locale/ar/LC_MESSAGES/django.po
mezzanine/accounts/locale/bg/LC_MESSAGES/django.mo
mezzanine/accounts/locale/bg/LC_MESSAGES/django.po
mezzanine/accounts/locale/ca/LC_MESSAGES/django.mo
mezzanine/accounts/locale/ca/LC_MESSAGES/django.po
mezzanine/accounts/locale/cs/LC_MESSAGES/django.mo
mezzanine/accounts/locale/cs/LC_MESSAGES/django.po
mezzanine/accounts/locale/da/LC_MESSAGES/django.mo
mezzanine/accounts/locale/da/LC_MESSAGES/django.po
mezzanine/accounts/locale/de/LC_MESSAGES/django.mo
mezzanine/accounts/locale/de/LC_MESSAGES/django.po
mezzanine/accounts/locale/en/LC_MESSAGES/django.mo
mezzanine/accounts/locale/en/LC_MESSAGES/django.po
mezzanine/accounts/locale/eo/LC_MESSAGES/django.mo
mezzanine/accounts/locale/eo/LC_MESSAGES/django.po
mezzanine/accounts/locale/es/LC_MESSAGES/django.mo
mezzanine/accounts/locale/es/LC_MESSAGES/django.po
